pyconfigloader/__init__.py
pyconfigloader-0.2.0.dist-info/LICENSE
pyconfigloader-0.2.0.dist-info/METADATA
pyconfigloader-0.2.0.dist-info/WHEEL
pyconfigloader-0.2.0.dist-info/RECORD
